{"noiseKey":{"private":{"type":"Buffer","data":"oKrSrINQKyJj4H2FhlcYfk8LPvE8C8YWW9PKSrfSLGw="},"public":{"type":"Buffer","data":"p6OHdgTeQRgQqtB4SkTJkdZFhg77o4qwAXeZcKJl/ho="}},"pairingEphemeralKeyPair":{"private":{"type":"Buffer","data":"YEEEblv1s1o+FN+/Hp1gavevSzprSL6+Yvwl08523lE="},"public":{"type":"Buffer","data":"zMtYzPpccPNOXRezRnuWkF6Awp6eyXN54uJX+BYqXyk="}},"signedIdentityKey":{"private":{"type":"Buffer","data":"qLAZVgUKFt0DMNIlkDunlMNOjjfEQyb6LYRWW0joqWY="},"public":{"type":"Buffer","data":"7xUDZXby/sKws6PMMDCyPY9lvGb4U3ZGbBOmtExKlHs="}},"signedPreKey":{"keyPair":{"private":{"type":"Buffer","data":"wK8fpOLLGe4Eyrml3BS3NHIxZ9Rl73I3bpGH6T5hK0E="},"public":{"type":"Buffer","data":"Jv59Vx/ebCxM05sDnp+WM2GAXmzbleFM/qy1GxIaNlw="}},"signature":{"type":"Buffer","data":"8UBGdtxD5CgVCrLfp0WVIuECk2C4hXUb7CQxnOVbureUcDg7HuZ3eZOy+PMOm52Iux3uPb9VJ1O9BRJw/Mlmig=="},"keyId":1},"registrationId":154,"advSecretKey":"G6Y74JNKlt5GBlaWXz9iETk8XrLlR8+JpV3UnPlRPtQ=","processedHistoryMessages":[{"key":{"remoteJid":"224621740232@s.whatsapp.net","fromMe":true,"id":"3AB9637C16C51D4D389B","participant":"","addressingMode":"pn"},"messageTimestamp":1783874489},{"key":{"remoteJid":"224621740232@s.whatsapp.net","fromMe":true,"id":"3A4CC040671FD249467D","participant":"","addressingMode":"pn"},"messageTimestamp":1783874492},{"key":{"remoteJid":"224621740232@s.whatsapp.net","fromMe":true,"id":"3A9C7D11D1E1485A501C","participant":"","addressingMode":"pn"},"messageTimestamp":1783874494},{"key":{"remoteJid":"224621740232@s.whatsapp.net","fromMe":true,"id":"3AB77BCBB8F75AF6BA0B","participant":"","addressingMode":"pn"},"messageTimestamp":1783874494},{"key":{"remoteJid":"224621740232@s.whatsapp.net","fromMe":true,"id":"3A9D9204FF63E45EB46A","participant":"","addressingMode":"pn"},"messageTimestamp":1783874513},{"key":{"remoteJid":"224621740232@s.whatsapp.net","fromMe":true,"id":"3AB7FAFEAF7DF78BBEE2","participant":"","addressingMode":"pn"},"messageTimestamp":1783874536},{"key":{"remoteJid":"224621740232@s.whatsapp.net","fromMe":true,"id":"3A41EC0A371232D58564","participant":"","addressingMode":"pn"},"messageTimestamp":1783874549},{"key":{"remoteJid":"224621740232@s.whatsapp.net","fromMe":true,"id":"3AB6800F0E4B50A3158B","participant":"","addressingMode":"pn"},"messageTimestamp":1783874559},{"key":{"remoteJid":"224621740232@s.whatsapp.net","fromMe":true,"id":"3A26D48D5E8DEAA9EF0D","participant":"","addressingMode":"pn"},"messageTimestamp":1783874637},{"key":{"remoteJid":"224621740232@s.whatsapp.net","fromMe":true,"id":"3AC7B3F5BFB582CDF0C8","participant":"","addressingMode":"pn"},"messageTimestamp":1783874637}],"nextPreKeyId":863,"firstUnuploadedPreKeyId":863,"accountSyncCounter":1,"accountSettings":{"unarchiveChats":false},"registered":false,"account":{"details":"CI/ajLIDEK2Hz9IGGBMgACgA","accountSignatureKey":"mK7KVuNbMKVQ2x0OcIZd3EK2zZqGJRahG2+lAVdajjs=","accountSignature":"GyMcaJoqYkMaWKaMP9IMlZOI8Iuox3sCvvljKw+W6C+cA3vRvN8B7a6fCUj5m+L+hCC+yqDB+lJyr/FTtyc2gA==","deviceSignature":"1NF6b5m4GvsgPVtPui+51o6Qn/8WzGmkGHEmHU5Viyw5J9ahn1PXiPkvC2ZUbg5GC0ltxwnRay/C33y77Mw1jA=="},"me":{"id":"224621740232:27@s.whatsapp.net","lid":"32058323800168:27@lid","name":"Øūmåŕ Camara"},"signalIdentities":[{"identifier":{"name":"32058323800168:27@lid","deviceId":0},"identifierKey":{"type":"Buffer","data":"BZiuylbjWzClUNsdDnCGXdxCts2ahiUWoRtvpQFXWo47"}}],"platform":"iphone","routingInfo":{"type":"Buffer","data":"CAsICAgJ"},"lastAccountSyncTimestamp":1783874613,"lastPropHash":"4egXDY","myAppStateKeyId":"AAAAAHkK"}